q3rconlib/__init__.py
q3rconlib/base.py
q3rconlib/error.py
q3rconlib/packet/__init__.py
q3rconlib/packet/packet.py
q3rconlib/packet/request.py
q3rconlib/packet/response.py
q3rconlib/py.typed
q3rconlib/rcon.py
q3rconlib/util.py
q3rconlib-1.0.0.dist-info/LICENSE
q3rconlib-1.0.0.dist-info/METADATA
q3rconlib-1.0.0.dist-info/WHEEL
q3rconlib-1.0.0.dist-info/RECORD
