Metadata-Version: 2.3
Name: q3rconlib
Version: 1.0.0
Summary: A Quake3 RCON interface in Python
License: MIT
Author: onyx-and-iris
Author-email: code@onyxandiris.online
Requires-Python: >=3.11
Classifier: License :: OSI Approved :: MIT License
Classifier: Programming Language :: Python :: 3
Classifier: Programming Language :: Python :: 3.11
Classifier: Programming Language :: Python :: 3.12
Classifier: Programming Language :: Python :: 3.13
